wn_smart_meter/__init__.py
wn_smart_meter/auth.py
wn_smart_meter/base_client.py
wn_smart_meter/client.py
wn_smart_meter/exceptions.py
wn_smart_meter/models/__init__.py
wn_smart_meter/models/device.py
wn_smart_meter/models/metering_point.py
wiener_netze_smart_meter-0.1.0.dist-info/METADATA
wiener_netze_smart_meter-0.1.0.dist-info/WHEEL
wiener_netze_smart_meter-0.1.0.dist-info/top_level.txt
wiener_netze_smart_meter-0.1.0.dist-info/RECORD
