Metadata-Version: 2.4
Name: wiener-netze-smart-meter
Version: 0.1.0
Summary: Add your description here
Requires-Python: >=3.11
Requires-Dist: httpx>=0.28.1
Requires-Dist: pydantic>=2.11.7
